CHANGES.txt
MANIFEST.in
README.md
setup.cfg
setup.py
pyStock/__init__.py
pyStock/factories.py
pyStock/fields.py
pyStock.egg-info/PKG-INFO
pyStock.egg-info/SOURCES.txt
pyStock.egg-info/dependency_links.txt
pyStock.egg-info/not-zip-safe
pyStock.egg-info/pbr.json
pyStock.egg-info/requires.txt
pyStock.egg-info/top_level.txt
pyStock/models/__init__.py
pyStock/models/account.py
pyStock/models/events.py
pyStock/models/money.py
pyStock/scripts/__init__.py
pyStock/scripts/old_script.py
pystock.egg-info/SOURCES.txt
tests/__init__.py
tests/test_account.py
tests/test_money.py
tests/test_order.py