Metadata-Version: 1.1
Name: pystock
Version: 0.1.4
Summary: A stock market model for persistence using SQLAlchemy
Home-page: www.lazzaroleonardo.com.ar
Author: Leonardo Lazzaro
Author-email: lazzaroleonardo@gmail.com
License: UNKNOWN
Keywords: stock market model persistence
Platform: UNKNOWN
Classifier: Programming Language :: Python
Classifier: Topic :: Office/Business :: Financial
